servicepytan/__init__.py
servicepytan/_dates.py
servicepytan/attachments.py
servicepytan/auth.py
servicepytan/data.py
servicepytan/reports.py
servicepytan/requests.py
servicepytan/summary.py
servicepytan/utils.py
servicepytan-0.4.2.dist-info/licenses/AUTHORS.rst
servicepytan-0.4.2.dist-info/licenses/LICENSE
servicepytan-0.4.2.dist-info/METADATA
servicepytan-0.4.2.dist-info/WHEEL
servicepytan-0.4.2.dist-info/entry_points.txt
servicepytan-0.4.2.dist-info/top_level.txt
servicepytan-0.4.2.dist-info/RECORD
